googletrends_ai.py
googletrends_ai-0.0.4.dist-info/METADATA
googletrends_ai-0.0.4.dist-info/WHEEL
googletrends_ai-0.0.4.dist-info/entry_points.txt
googletrends_ai-0.0.4.dist-info/top_level.txt
googletrends_ai-0.0.4.dist-info/RECORD
