Metadata-Version: 2.1
Name: googletrends-ai
Version: 0.0.4
Summary: The graph shows how often the entered word or phrase is searched in Google Trend
Home-page: https://github.com/spcnkonno/googletrends_ai
Author: spcnkonno
Author-email: nkonno@sciencepark.co.jp
License: UNKNOWN
Project-URL: Bug Tracker, https://github.com/spcnkonno/googletrends_ai
Platform: UNKNOWN
Classifier: Programming Language :: Python :: 3
Classifier: License :: OSI Approved :: MIT License
Classifier: Operating System :: OS Independent
Requires-Python: >=3.8.10
